pybillboard_js/__init__.py
pybillboard_js/billboarder.py
pybillboard_js/exceptions.py
pybillboard_js/functions.py
pybillboard_js/logger.py
pybillboard_js/prototypes.py
pybillboard_js-0.1.0a9.dist-info/DESCRIPTION.rst
pybillboard_js-0.1.0a9.dist-info/METADATA
pybillboard_js-0.1.0a9.dist-info/RECORD
pybillboard_js-0.1.0a9.dist-info/WHEEL
pybillboard_js-0.1.0a9.dist-info/metadata.json
pybillboard_js-0.1.0a9.dist-info/top_level.txt
